red_web_dashboard-1.8.1.dist-info/licenses/LICENSE
reddash/__init__.py
reddash/__main__.py
reddash/app/__init__.py
reddash/app/app.py
reddash/app/pagination.py
reddash/app/task_manager.py
reddash/app/utils.py
reddash/app/base/__init__.py
reddash/app/base/routes.py
reddash/app/login/__init__.py
reddash/app/login/routes.py
reddash/app/static/assets/.gitkeep
reddash/app/static/assets/biometric-icon.svg
reddash/app/static/assets/error-403.gif
reddash/app/static/assets/error-404.gif
reddash/app/static/assets/error-500.gif
reddash/app/static/assets/gulpfile.js
reddash/app/static/assets/icon-documentation.svg
reddash/app/static/assets/oauth.png
reddash/app/static/assets/pdf.svg
reddash/app/static/assets/random.svg
reddash/app/static/assets/robots.txt
reddash/app/static/assets/css/argon-dashboard.css
reddash/app/static/assets/css/argon-dashboard.css.map
reddash/app/static/assets/css/argon-dashboard.min.css
reddash/app/static/assets/css/nucleo-icons.css
reddash/app/static/assets/css/nucleo-svg.css
reddash/app/static/assets/css/simplemde.min.css
reddash/app/static/assets/css/themes/background_theme_dark.css
reddash/app/static/assets/css/themes/background_theme_white.css
reddash/app/static/assets/css/themes/sidenav_theme_dark.css
reddash/app/static/assets/css/themes/sidenav_theme_white.css
reddash/app/static/assets/fonts/nucleo-icons.eot
reddash/app/static/assets/fonts/nucleo-icons.svg
reddash/app/static/assets/fonts/nucleo-icons.ttf
reddash/app/static/assets/fonts/nucleo-icons.woff
reddash/app/static/assets/fonts/nucleo-icons.woff2
reddash/app/static/assets/fonts/nucleo.eot
reddash/app/static/assets/fonts/nucleo.ttf
reddash/app/static/assets/fonts/nucleo.woff
reddash/app/static/assets/fonts/nucleo.woff2
reddash/app/static/assets/js/argon-dashboard.js
reddash/app/static/assets/js/argon-dashboard.js.map
reddash/app/static/assets/js/core/bootstrap.min.js
reddash/app/static/assets/js/core/jquery.min.js
reddash/app/static/assets/js/core/popper.min.js
reddash/app/static/assets/js/plugins/Chart.extension.js
red_web_dashboard-1.8.1.dist-info/METADATA
red_web_dashboard-1.8.1.dist-info/WHEEL
red_web_dashboard-1.8.1.dist-info/entry_points.txt
red_web_dashboard-1.8.1.dist-info/top_level.txt
red_web_dashboard-1.8.1.dist-info/RECORD
