Metadata-Version: 2.4
Name: Red-Web-Dashboard
Version: 1.8.1
Summary: An easy-to-use interactive web Dashboard to control your Red bot!
Home-page: https://github.com/AAA3A-AAA3A/Red-Web-Dashboard
Author: AAA3A & Neuro Assassin
License: AGPL-3.0
Project-URL: Third Party Discord Server, https://discord.gg/red-cog-support-240154543684321280
Project-URL: Documentation, https://red-web-dashboard.readthedocs.io/en/latest/
Project-URL: Donate on Buy Me a Coffee, https://www.buymeacoffee.com/aaa3a
Project-URL: Source Code, https://github.com/AAA3A-AAA3A/Red-Web-Dashboard
Project-URL: Red Source Code, https://github.com/Cog-Creators/Red-DiscordBot
Project-URL: Red Discord Server, https://discord.gg/red
Classifier: Development Status :: 3 - Alpha
Classifier: Framework :: Flask
Classifier: Intended Audience :: Developers
Classifier: Intended Audience :: End Users/Desktop
Classifier: License :: OSI Approved :: GNU Affero General Public License v3
Classifier: Natural Language :: English
Classifier: Operating System :: MacOS :: MacOS X
Classifier: Operating System :: Microsoft :: Windows
Classifier: Operating System :: POSIX :: Linux
Classifier: Programming Language :: Python :: 3.8
Classifier: Topic :: Internet :: WWW/HTTP :: Dynamic Content :: Content Management System
Requires-Python: >=3.8.1
License-File: LICENSE
Requires-Dist: flask[async]
Requires-Dist: waitress
Requires-Dist: websocket-client
Requires-Dist: Flask-Babel
Requires-Dist: pygments
Requires-Dist: PyJWT
Requires-Dist: flask-login
Requires-Dist: flask_wtf
Requires-Dist: WTForms
Requires-Dist: python-Levenshtein
Requires-Dist: fernet
Requires-Dist: rich
Requires-Dist: rapidfuzz
Requires-Dist: fuzzywuzzy
Requires-Dist: aiohttp
Requires-Dist: django-user-agents
Requires-Dist: Flask-Bootstrap
Requires-Dist: markdown
Requires-Dist: bleach
Requires-Dist: flask-moment
Requires-Dist: flask-talisman
Requires-Dist: flask-sitemapper
Provides-Extra: style
Requires-Dist: black==19.10b0; extra == "style"
Provides-Extra: docs
Requires-Dist: Sphinx==4.4.0; extra == "docs"
Requires-Dist: sphinx-rtd-theme==1.0.0; extra == "docs"
Requires-Dist: sphinx-prompt==1.5.0; extra == "docs"
Dynamic: license-file
